flag_morph-0.2.0.dist-info/METADATA
flag_morph-0.2.0.dist-info/WHEEL
flag_morph-0.2.0.dist-info/entry_points.txt
flag_morph/__init__.py
flag_morph/extract.py
flag_morph-0.2.0.dist-info/RECORD
