Metadata-Version: 2.1
Name: flag-morph
Version: 0.2.0
Summary: A morphological analysis module for the phrases on impeachment flags born in South Korea's unprecedented martial law situation on December 3, 2024.
Author-Email: ppabam <tom@diginori.com>
License: Apache License 2.0
Requires-Python: >=3.10
Requires-Dist: kiwipiepy>=0.20.3
